src/dataset_handler/__init__.py
src/dataset_handler/download.py
src/dataset_handler/entrypoint.py
src/dataset_handler/extract.py
dataset_handler-0.1.0.dist-info/LICENSE
dataset_handler-0.1.0.dist-info/METADATA
dataset_handler-0.1.0.dist-info/WHEEL
dataset_handler-0.1.0.dist-info/entry_points.txt
dataset_handler-0.1.0.dist-info/RECORD
