Metadata-Version: 2.1
Name: dataset-handler
Version: 0.1.0
Summary: Utility package for managing dataset
Author: onlinejudge95
Author-email: onlinejudge95@gmail.com
Requires-Python: >=3.9,<4.0
Classifier: Programming Language :: Python :: 3
Classifier: Programming Language :: Python :: 3.9
Classifier: Programming Language :: Python :: 3.10
Classifier: Programming Language :: Python :: 3.11
Classifier: Programming Language :: Python :: 3.12
Requires-Dist: click (==8.1.7)
Requires-Dist: httpx (==0.27.0)
Requires-Dist: opencv-python-headless (==4.10.0.84)
